.gitignore
CHANGES.rst
LICENSE
README.rst
release.sh
setup.py
test-requirements.txt
tox.ini
defrost/__init__.py
defrost/cli.py
defrost/package.py
defrost/pipfreeze.py
defrost/validation.py
defrost.egg-info/PKG-INFO
defrost.egg-info/SOURCES.txt
defrost.egg-info/dependency_links.txt
defrost.egg-info/entry_points.txt
defrost.egg-info/not-zip-safe
defrost.egg-info/requires.txt
defrost.egg-info/top_level.txt
tests/pipfreeze_no_matching_req.txt
tests/pipfreeze_satisfied_matching_req.txt
tests/pipfreeze_unsatisfied_matching_req.txt
tests/pipfreeze_unsatisfied_reqs_and_contains_links.txt
tests/pipfreeze_unsatisfied_reqs_with_severity.txt
tests/reqs.yml
tests/reqs_invalid_data.yml
tests/reqs_unparsable.yml
tests/test_cli.py
tests/test_package.py
tests/test_pipfreeze.py
tests/test_requirement.py
tests/test_validate.py