Metadata-Version: 1.1
Name: defrost
Version: 0.3.1
Summary: A tool to audit pip freeze outputs and test version requirements
Home-page: https://github.com/SurveyMonkey/defrost
Author: Alex Conrad
Author-email: alexandre@surveymonkey.com
License: MIT License
Keywords: defrost pip freeze output audit version requirements deprecate
Platform: UNKNOWN
Classifier: Topic :: Software Development :: Libraries :: Python Modules
Classifier: License :: OSI Approved :: MIT License
Classifier: Natural Language :: English
Classifier: Operating System :: OS Independent
Classifier: Programming Language :: Python
Classifier: Programming Language :: Python :: 2.7
Classifier: Programming Language :: Python :: 3
Classifier: Programming Language :: Python :: 3.3
Classifier: Programming Language :: Python :: 3.4
